{"name":"Web-lms","tagline":"A learning management system made compatible to be used for Primary, Secondary and Higher Secondary Educational Institutions in Bangladesh.","body":"### Web LMS\r\n### An easy to use learning management system\r\n\r\nThis is a learning management system, I created recently so that primary, secondary and higher secondary level educational institutions can use this site for reaching further.\r\n\r\n**This is just a prototype. I would be happy to make it evolved into something better which can be our next step to reaching students from less privileged area. But it would be nicer to have a sponsorship, little marketing to make people know about it.**\r\n\r\nHere are some screenshots:\r\n![Web LMS Screenshots](http://imgur.com/a/pi814)\r\n\r\n<blockquote class=\"imgur-embed-pub\" lang=\"en\" data-id=\"a/pi814\"><a href=\"//imgur.com/a/pi814\">Web LMS for Bangladesh</a></blockquote><script async src=\"//s.imgur.com/min/embed.js\" charset=\"utf-8\"></script>","google":"","note":"Don't delete this file! It's used internally to help with page regeneration."}